hieronymus/__init__.py
hieronymus/__main__.py
hieronymus/_progs.py
hieronymus/drafts/gitignore.txt
hieronymus/drafts/init.txt
hieronymus/drafts/license.txt
hieronymus/drafts/main.txt
hieronymus-1.0.2.dist-info/LICENSE.txt
hieronymus-1.0.2.dist-info/METADATA
hieronymus-1.0.2.dist-info/WHEEL
hieronymus-1.0.2.dist-info/top_level.txt
hieronymus-1.0.2.dist-info/RECORD
