Metadata-Version: 2.1
Name: hieronymus
Version: 1.0.2
Summary: Create a minimal python package.
Author-email: Johannes <johannes-programming@mailfence.org>
License: The MIT License (MIT)
Project-URL: Download, https://pypi.org/project/hieronymus/#files
Project-URL: Source, https://github.com/johannes-programming/hieronymus
Classifier: License :: OSI Approved :: MIT License
Classifier: Programming Language :: Python
Classifier: Programming Language :: Python :: 3
Requires-Python: >=3.11
License-File: LICENSE.txt
Requires-Dist: fileunity >=1.1
